LICENSE
dbsavior/DbBackupRestoreBot.py
dbsavior/__init__.py
dbsavior/db/DbManagerInterface.py
dbsavior/db/PostgresDbManager.py
dbsavior/db/__init__.py
dbsavior/main.py
dbsavior/storage/LocalStorageEngine.py
dbsavior/storage/ProgressPercentage.py
dbsavior/storage/S3StorageEngine.py
dbsavior/storage/StorageEngineInterface.py
dbsavior/storage/__init__.py
dbsavior/util.py
dbsavior-0.1.1.dist-info/LICENSE
dbsavior-0.1.1.dist-info/WHEEL
dbsavior-0.1.1.dist-info/METADATA
dbsavior-0.1.1.dist-info/RECORD
