Metadata-Version: 2.1
Name: dbsavior
Version: 0.1.1
Summary: This backup restore bot can backup/restore a database and upload/download the backup file to/from a remote storage engine
Home-page: https://github.com/pengfei99/K8sCronJobPostgresBackup
License: APACHE V2
Keywords: database,s3,backup,restore
Author: Liu Pengfei
Author-email: liu.pengfei@hotmail.fr
Requires-Python: >=3.8,<4.0
Classifier: License :: OSI Approved :: Apache Software License
Classifier: License :: Other/Proprietary License
Classifier: Operating System :: OS Independent
Classifier: Programming Language :: Python :: 3
Classifier: Programming Language :: Python :: 3.10
Classifier: Programming Language :: Python :: 3.8
Classifier: Programming Language :: Python :: 3.9
Requires-Dist: boto3 (>=1.20.27,<2.0.0)
Requires-Dist: psycopg2-binary (>=2.9.3,<3.0.0)
Project-URL: Repository, https://github.com/pengfei99/K8sCronJobPostgresBackup
